Metadata-Version: 2.1
Name: topsis-101703551
Version: 2.1.0
Summary: A Python package to rank ML models/choices using topsis technique
Home-page: https://github.com/sirishbhu/topsis
Author: Sirish Bhudolia
Author-email: sirishbhudolia88@gmail.com
License: MIT
Platform: UNKNOWN
Classifier: License :: OSI Approved :: MIT License
Classifier: Programming Language :: Python :: 3
Classifier: Programming Language :: Python :: 3.7
